certbot_inwx_hook/__init__.py
certbot_inwx_hook/certbot_inwx_hook.sample.ini
certbot_inwx_hook/constants.py
certbot_inwx_hook/inwx.py
certbot_inwx_hook/inwx_challenge.py
certbot_inwx_hook/main.py
certbot_inwx_hook-1.0.2.dist-info/DESCRIPTION.rst
certbot_inwx_hook-1.0.2.dist-info/METADATA
certbot_inwx_hook-1.0.2.dist-info/RECORD
certbot_inwx_hook-1.0.2.dist-info/WHEEL
certbot_inwx_hook-1.0.2.dist-info/entry_points.txt
certbot_inwx_hook-1.0.2.dist-info/metadata.json
certbot_inwx_hook-1.0.2.dist-info/top_level.txt
